{
  "project_info": {
    "project_number": "904888305046",
    "project_id": "carsdata-da193",
    "storage_bucket": "carsdata-da193.appspot.com"
  },
  "client": [
    {
      "client_info": {
        "mobilesdk_app_id": "1:904888305046:android:a8b77f3791708432ae09b7",
        "android_client_info": {
          "package_name": "com.bignerdranch.android.carinformation"
        }
      },
      "oauth_client": [
        {
          "client_id": "904888305046-q78n73fsdds92brvapueke4tbjf745er.apps.googleusercontent.com",
          "client_type": 3
        }
      ],
      "api_key": [
        {
          "current_key": "AIzaSyBDdu7XHIMyNTvDKSMpNtKKPq1YPYm2mDM"
        }
      ],
      "services": {
        "appinvite_service": {
          "other_platform_oauth_client": [
            {
              "client_id": "904888305046-q78n73fsdds92brvapueke4tbjf745er.apps.googleusercontent.com",
              "client_type": 3
            }
          ]
        }
      }
    }
  ],
  "configuration_version": "1"
}